llmonad/__init__.py
llmonad-0.0.1.dist-info/METADATA
llmonad-0.0.1.dist-info/WHEEL
llmonad-0.0.1.dist-info/top_level.txt
llmonad-0.0.1.dist-info/RECORD
